{
  "kind": "collectionType",
  "collectionName": "reviews",
  "info": {
    "singularName": "review",
    "pluralName": "reviews",
    "displayName": "Review",
    "description": ""
  },
  "options": {
    "draftAndPublish": true
  },
  "pluginOptions": {},
  "attributes": {
    "firstName": {
      "type": "string"
    },
    "email": {
      "type": "string"
    },
    "content": {
      "type": "text"
    },
    "photo": {
      "type": "media",
      "multiple": false,
      "required": false,
      "allowedTypes": [
        "images",
        "files",
        "videos",
        "audios"
      ]
    },
    "rate": {
      "type": "integer"
    },
    "product": {
      "type": "relation",
      "relation": "oneToOne",
      "target": "api::product.product"
    },
    "lastName": {
      "type": "string"
    }
  }
}
